pysparkpipe/__init__.py
pysparkpipe/exc.py
pysparkpipe/pipeline/__init__.py
pysparkpipe/pipeline/layers.py
pysparkpipe/pipeline/pipeline.py
pysparkpipe/pipeline/utils.py
pysparkpipe-0.1.4.dist-info/METADATA
pysparkpipe-0.1.4.dist-info/WHEEL
pysparkpipe-0.1.4.dist-info/RECORD
