Metadata-Version: 2.1
Name: pysparkpipe
Version: 0.1.4
Summary: Flow orchestrator for data transformations within the context of pyspark.sql.GroupedData.applyInPandas
Author: Santiago Armstrong
Author-email: santiagoarmstrong@gmail.com
Requires-Python: >=3.8.1,<4.0
Classifier: Programming Language :: Python :: 3
Classifier: Programming Language :: Python :: 3.9
Classifier: Programming Language :: Python :: 3.10
Classifier: Programming Language :: Python :: 3.11
Classifier: Programming Language :: Python :: 3.12
Requires-Dist: pandas (>=1.4.3,<2.0.0)
Requires-Dist: pandera (>=0.16.1,<0.17.0)
Requires-Dist: pyarrow (>=7.0.0)
Requires-Dist: pyspark (>=3.2.1)
Requires-Dist: typeguard (>=4.1.1,<5.0.0)
